{
  "엔블로정은 국내 최초로 개발된 SGLT-2 억제제 국산 신약이다.": {
    "answer": "O",
    "category": "엔블로"
  },
  "Dapagliflozin 10mg을 엔블로 (Enavogliflozin 0.3mg)로 스위칭 하여도 혈당강하효과는 유지 되나요": {
    "answer": "O",
    "category": "엔블로"
  },
  "엔블로의 특장점이 아닌 것은 어떤 것인가요": {
    "answer": "3",
    "category": "엔블로"
  },
  "프리스타일 리브레2는 공장 보정이 완료되어 있는 제품으로, 손가락 채혈 보정 없이 바로 사용이 가능하다": {
    "answer": "O",
    "category": "프리스타일 리브레"
  },
  "프리스타일 리브레2는 최대 14일간 착용 가능하다": {
    "answer": "O",
    "category": "프리스타일 리브레"
  },
  "프리스타일 리브레2는 ( )분 단위로 혈당 수치를 측정하여 저혈당과 고혈당의 순간을 알려주어 급격한 혈당 변동성에 신속하게 대응할 수 있다": {
    "answer": "1",
    "category": "프리스타일 리브레"
  }
}